uc_card/__init__.py
uc_card/example.py
uc_card/frontend/build/asset-manifest.json
uc_card/frontend/build/bootstrap.min.css
uc_card/frontend/build/index.html
uc_card/frontend/build/static/css/main.386778f9.css
uc_card/frontend/build/static/css/main.386778f9.css.map
uc_card/frontend/build/static/js/main.22353c77.js
uc_card/frontend/build/static/js/main.22353c77.js.LICENSE.txt
uc_card/frontend/build/static/js/main.22353c77.js.map
uc_card/frontend/build/static/js/main.b35edf9a.js
uc_card/frontend/build/static/js/main.b35edf9a.js.LICENSE.txt
uc_card/frontend/build/static/js/main.b35edf9a.js.map
uc_card/frontend/build/static/media/Flaticon.23693237529cde1eeef1.eot
uc_card/frontend/build/static/media/Flaticon.59cc8aa9084f59706a52.ttf
uc_card/frontend/build/static/media/Flaticon.5b9118b487105304f2b7.svg
uc_card/frontend/build/static/media/Flaticon.ca86721fde1c0713ea4d.woff
uc_card/frontend/build/static/media/Simple-Line-Icons4c82.1334d7641f5b94d8d01d.woff
uc_card/frontend/build/static/media/Simple-Line-Icons4c82.51b9ac91d27d5ba0b73f.svg
uc_card/frontend/build/static/media/Simple-Line-Icons4c82.7f0913d4da1704f5de7f.ttf
uc_card/frontend/build/static/media/Simple-Line-Icons4c82.a736074699ec538328fe.woff2
uc_card/frontend/build/static/media/Simple-Line-Icons4c82.cb4840b543cf18677ced.eot
uc_card/frontend/build/static/media/Simple-Line-Iconsd41d.cb4840b543cf18677ced.eot
uc_card/frontend/build/static/media/avasta.35f800799755b8fcc773.woff
uc_card/frontend/build/static/media/avasta.52f0e64f452232316f1b.svg
uc_card/frontend/build/static/media/avasta.568a19c253fb383257be.eot
uc_card/frontend/build/static/media/avasta.d2283edad95d676873d7.woff2
uc_card/frontend/build/static/media/avasta.d9a081013ad1508ed10e.ttf
uc_card/frontend/build/static/media/fontawesome-webfont3e6e.1e59d2330b4c6deb84b3.ttf
uc_card/frontend/build/static/media/fontawesome-webfont3e6e.20fd1704ea223900efa9.woff2
uc_card/frontend/build/static/media/fontawesome-webfont3e6e.8b43027f47b20503057d.eot
streamlit_uc_card-0.0.2.dist-info/LICENSE
streamlit_uc_card-0.0.2.dist-info/METADATA
streamlit_uc_card-0.0.2.dist-info/WHEEL
streamlit_uc_card-0.0.2.dist-info/top_level.txt
streamlit_uc_card-0.0.2.dist-info/RECORD
